ditrans2cldf/__init__.py
ditrans2cldf/bibliography.py
ditrans2cldf/config.py
ditrans2cldf/csv_input.py
ditrans2cldf/excel_input.py
ditrans2cldf/process.py
ditrans2cldf/scaffold.py
ditrans2cldf/dataset_template/+prefix+_+id+.py_tmpl
ditrans2cldf/dataset_template/.gitignore
ditrans2cldf/dataset_template/setup.cfg
ditrans2cldf/dataset_template/setup.py_tmpl
ditrans2cldf/dataset_template/test.py
ditrans2cldf/dataset_template/cldf/.gitattributes
ditrans2cldf/dataset_template/cldf/README.md
ditrans2cldf/dataset_template/etc/README.md
ditrans2cldf/dataset_template/etc/config.json
ditrans2cldf/dataset_template/raw/README.md
ditrans2cldf-1.0.2.dist-info/LICENSE
ditrans2cldf-1.0.2.dist-info/METADATA
ditrans2cldf-1.0.2.dist-info/WHEEL
ditrans2cldf-1.0.2.dist-info/entry_points.txt
ditrans2cldf-1.0.2.dist-info/top_level.txt
ditrans2cldf-1.0.2.dist-info/RECORD
